{
	"id": "GENERATE_UUID",
	"name": "REPLACE_WITH_DOMAIN",
	"values": [
		{
			"key": "host",
			"value": "https://REPLACE_WITH_DOMAIN",
			"type": "default",
			"enabled": true
		},
		{
			"key": "apikey",
			"value": "REPLACE_WITH_APIKEY",
			"type": "default",
			"enabled": true
		},
		{
			"key": "lms_client_secret",
			"value": "lmsREPLACE_WITH_SECRET",
			"type": "default",
			"enabled": true
		},
		{
			"key": "admin_client_id",
			"value": "direct-grant",
			"type": "default",
			"enabled": true
		},
		{
			"key": "admin_client_secret",
			"value": "direct-grantREPLACE_WITH_SECRET",
			"type": "default",
			"enabled": true
		},
		{
			"key": "admin_grant_type",
			"value": "password",
			"type": "default",
			"enabled": true
		},
		{
			"key": "admin_username",
			"value": "REPLACE_WITH_KEYCLOAK_ADMIN",
			"type": "default",
			"enabled": true
		},
		{
			"key": "admin_password",
			"value": "REPLACE_WITH_KEYCLOAK_PASSWORD",
			"type": "default",
			"enabled": true
		},
		{
			"key": "blob_store_path",
			"value": "BLOB_STORE_PATH",
			"type": "default",
			"enabled": true
		},
		{
			"key": "public_container_name",
			"value": "PUBLIC_CONTAINER_NAME",
			"type": "default",
			"enabled": true
		}

	],
	"_postman_variable_scope": "environment"
}